METER/__init__.py
METER/plots.py
METER/summaries.py
METER/table.py
METER/wrangler.py
METER-0.6.5.dist-info/LICENSE.txt
METER-0.6.5.dist-info/METADATA
METER-0.6.5.dist-info/WHEEL
METER-0.6.5.dist-info/top_level.txt
METER-0.6.5.dist-info/RECORD
