Metadata-Version: 2.1
Name: METER
Version: 0.6.5
Summary: Multi-state Estimates for Time-to-Event Research
Home-page: https://github.com/MR236/METER
Author: Malcolm Risk
Author-email: mr236@st-andrews.ac.uk
License: CC0
Project-URL: Documentation, https://meter1.readthedocs.io/en/latest/
Platform: UNKNOWN
Requires-Dist: numpy
Requires-Dist: pandas
Requires-Dist: matplotlib
